LICENSE.txt
README.md
setup.cfg
setup.py
gmi_ston.egg-info/PKG-INFO
gmi_ston.egg-info/SOURCES.txt
gmi_ston.egg-info/dependency_links.txt
gmi_ston.egg-info/requires.txt
gmi_ston.egg-info/top_level.txt
ston/__init__.py
ston/__swapper.py
ston/__ton_client.py
ston/client.py