Metadata-Version: 2.1
Name: gmi-ston
Version: 0.4.1
Summary: Interface to interact with STON.fi by GetMoney Inc.
Home-page: https://github.com/get-money-inc/ston-py
Author: GetMoney Inc.
Author-email: get.money.inc.official@gmail.com
License: UNKNOWN
Platform: UNKNOWN
Requires-Python: >=3.11
License-File: LICENSE.txt
